jsonmore/__init__.py
jsonmore/__main__.py
jsonmore/cli.py
jsonmore/colors.py
jsonmore/core.py
jsonmore/pager.py
jsonmore/py.typed
jsonmore/utils.py
jsonmore-1.0.3.dist-info/METADATA
jsonmore-1.0.3.dist-info/WHEEL
jsonmore-1.0.3.dist-info/entry_points.txt
jsonmore-1.0.3.dist-info/licenses/LICENSE
jsonmore-1.0.3.dist-info/RECORD
