Metadata-Version: 2.4
Name: jsonmore
Version: 1.0.3
Summary: A powerful command-line tool for reading, formatting, and analyzing JSON files with beautiful syntax highlighting, automatic error repair, and smart paging
Project-URL: Homepage, https://github.com/jasonacox/jsonmore
Project-URL: Documentation, https://github.com/jasonacox/jsonmore#readme
Project-URL: Repository, https://github.com/jasonacox/jsonmore.git
Project-URL: Bug Tracker, https://github.com/jasonacox/jsonmore/issues
Author-email: Jason Cox <jason@jasonacox.com>
Maintainer-email: Jason Cox <jason@jasonacox.com>
License: MIT License
License-File: LICENSE
Keywords: cli,formatting,json,repair,syntax-highlighting,validator
Classifier: Development Status :: 5 - Production/Stable
Classifier: Environment :: Console
Classifier: Intended Audience :: Developers
Classifier: Intended Audience :: System Administrators
Classifier: License :: OSI Approved :: MIT License
Classifier: Operating System :: OS Independent
Classifier: Programming Language :: Python :: 3
Classifier: Programming Language :: Python :: 3.8
Classifier: Programming Language :: Python :: 3.9
Classifier: Programming Language :: Python :: 3.10
Classifier: Programming Language :: Python :: 3.11
Classifier: Programming Language :: Python :: 3.12
Classifier: Topic :: Software Development :: Libraries :: Python Modules
Classifier: Topic :: Text Processing
Classifier: Topic :: Utilities
Requires-Python: >=3.8
Requires-Dist: colorama>=0.4.0
Provides-Extra: dev
Requires-Dist: black; extra == 'dev'
Requires-Dist: flake8; extra == 'dev'
Requires-Dist: mypy; extra == 'dev'
Requires-Dist: pytest>=6.0; extra == 'dev'
